{"0":{"id":"296000","code":"AINXF5OVG2","title":"Samsung Galaxy Gio 8 13 cm (3 2&amp;quot;) 150 GB Single SIM Silver White 1350 mAh","longdesc":"&lt;b&gt;Timeless Polished Design with 3.2&rdquo; HVGA Screen&lt;/b&gt;&lt;br/&gt;The polished design of this mobile, as well as its timeless look, is an extension of the your personal style. Not a mindless trend follower, you might demand a more classic look. The Gio satisfies your design aesthetics while also being ergonomically compact for easy portability and comfortable usage. The 3.2&rdquo; HVGA display is ideal for viewing video and browsing photos, too.&lt;br/&gt;&lt;br/&gt;&lt;b&gt;Powerful Performance w/ Borderless Networking&lt;/b&gt;&lt;br/&gt;You will enjoy the speed and rich performance of this mobile. No longer will you have to wait around for movies to load or applications to start - everything works quickly and hassle-free. Wi-Fi b/g/n provides faster web browsing with wider coverage than before, and HSDPA 7.2Mbps downloads large files quickly. Because of the larger battery life, you can do all of this and much more on a single battery charge.&lt;br/&gt;&lt;br/&gt;&lt;b&gt;Ultimate Integration&lt;/b&gt;&lt;br/&gt;A one-stop centre for all your messaging, the Social Hub offers you a quick glance status check of all their messages across various platforms including email, instant messaging, social networking and SMS. You won&rsquo;t have to view different calendars to get their schedule. Various online calendars including Facebook Events are all integrated onto one easy-to-check calendar. You won&rsquo;t have to look up two separate widgets to check the time and the weather thanks to the Hybrid widgets. Also, there&rsquo;s a widget to monitor data usage so the phone bill doesn&rsquo;t get too out of control.&lt;br/&gt;&lt;br/&gt;&lt;b&gt;Convenience Centre&lt;/b&gt;&lt;br/&gt;Allshare connects the mobile to TV, computer, stereo system, etc. on a home network so that all media content is shared easily. Typing is much easier, too. With SWYPE, you can input text much faster by swiping their finger across the letters on the screen instead of tapping each individual button.&lt;br/&gt;&lt;br/&gt;&lt;b&gt;Entertainment Centre&lt;/b&gt;&lt;br/&gt;With access to the mobile&rsquo;s many features, you will enjoy fun and entertainment around the clock. Everything from Google Mobile Services to over 2 million applications from the Android Market is available.","properties":[{"Sys_Num_Images":"2"},{"UPC":"8806085052734"},{"Brand":"Samsung"},{"Gallery Images":"4"},{"Pdf Files":"1"},{"Depth":"12.2 mm"},{"Display diagonal":"8.13 cm (3.2\")"},{"Display resolution":"320 x 480 pixels"},{"Height":"110.5 mm"},{"Product colour":"Silver,White"},{"Weight":"102 g"},{"Width":"57.5 mm"},{"Wi-Fi":"Yes"},{"Battery capacity":"1350 mAh"},{"Internal memory":"1350 mAh"},{"Compatible memory cards":"microSD (TransFlash)"},{"Bluetooth":"Yes"},{"3G":"Yes"},{"Audio formats supported":"AAC,MIDI,MP3,WAV"},{"Video formats supported":"3GP,H.263,H.264,MPEG4"},{"Wi-Fi standards":"802.11b,802.11g,Wi-Fi 4 (802.11n)"},{"Battery technology":"Lithium-Ion (Li-Ion)"},{"Display number of colours":"16.78 million colors"},{"USB port":"Yes"},{"2G standards":"EDGE,GPRS,GSM"},{"Bluetooth version":"3.0+EDR"},{"Data network":"3G"},{"Digital zoom":"3x"},{"FM radio":"Yes"},{"Form factor":"Bar"},{"MMS (Multimedia Messaging Service)":"Yes"},{"Rear camera type":"Single camera"},{"Standby time (2G)":"610 h"},{"Talk time (2G)":"10.6 h"},{"3G standards":"HSDPA"},{"4G":"No"},{"Assisted GPS (A-GPS)":"Yes"},{"Auto focus":"Yes"},{"E-mail":"Yes"},{"GPS (satellite)":"Yes"},{"Instant messaging (IM)":"Yes"},{"Maximum memory card size":"32 GB"},{"Personal info management (PIM)":"Alarm clock,Calculator,Calendar,Notes"},{"Platform":"Android"},{"Position location":"Yes"},{"Radio Data System (RDS)":"Yes"},{"Rear camera resolution (numeric)":"3 MP"},{"Short Message Service (SMS)":"Yes"},{"SIM card capability":"Single SIM"},{"Standby time (3G)":"460 h"},{"Subscription type":"No subscription"},{"Talk time (3G)":"6.6 h"},{"Text prediction system":"Yes"},{"Text prediction system type":"T9"},{"Touchscreen":"Yes"},{"USB version":"2.0"},{"Speakerphone":"Yes"},{"Maximum frame rate":"15 fps"},{"Internal storage capacity":"150 GB"},{"Video recording":"Yes"},{"Flight mode":"Yes"},{"Photo effects":"Black&White,Negative film,Neutral,Sepia"},{"White balance":"Auto,Cloudy,Daylight,Fluorescent,Incandescent"},{"Caller ID":"Yes"},{"2G bands (primary SIM)":"850,900,1800,1900 MHz"},{"USB mass storage":"Yes"},{"Touch technology":"Multi-touch"}],"breadcrumbs":[{"name":"Home","url":"/"}],"frequentlyBoughtTogether":[],"accessories":[],"alsoLike":[],"reviews":[]},"url":"http://demob2b2cpreview.avetti.io/preview/product/smartphones/samsung-galaxy-gio-8-13-cm-3-2-150-gb-single-sim-silver-white-1350-mah-ainxf5ovg2","productData":{"__Result":[{"additionalImages":"AINXF5OVG2-2.jpg","allowBackOrders":false,"alsoLikeItems":[],"attributes":[],"available":true,"cimage":"https://s3.ca-central-1.amazonaws.com/demob2b2cs3.avetti.ca/store/20180522154/assets/items/thumbnails/AINXF5OVG2.jpg","code":"AINXF5OVG2","discount":0,"discountItemGroup":"","discountItemType":"","enableDelOpts":"true","hiddenProperties":[{"itemid":0,"propdesc":"","propgroup":"","propid":0,"propname":"Created_By_Supplier","propnumber":165,"propvalue":"20181212828"},{"itemid":0,"propdesc":"","propgroup":"","propid":0,"propname":"Supplier_Item_Code","propnumber":166,"propvalue":"GT_S5660SWANEE"},{"itemid":0,"propdesc":"Sys_Num_Images","propgroup":"","propid":0,"propname":"Sys_Num_Images","propnumber":159,"propvalue":"2"}],"image":"https://s3.ca-central-1.amazonaws.com/demob2b2cs3.avetti.ca/store/20180522154/assets/items/images/AINXF5OVG2.jpg","image3":"https://s3.ca-central-1.amazonaws.com/demob2b2cs3.avetti.ca/store/20180522154/assets/items/largeimages/AINXF5OVG2.jpg","itemId":296000,"itemid":296000,"longdesc":"<b>Timeless Polished Design with 3.2” HVGA Screen</b><br/>The polished design of this mobile, as well as its timeless look, is an extension of the your personal style. Not a mindless trend follower, you might demand a more classic look. The Gio satisfies your design aesthetics while also being ergonomically compact for easy portability and comfortable usage. The 3.2” HVGA display is ideal for viewing video and browsing photos, too.<br/><br/><b>Powerful Performance w/ Borderless Networking</b><br/>You will enjoy the speed and rich performance of this mobile. No longer will you have to wait around for movies to load or applications to start - everything works quickly and hassle-free. Wi-Fi b/g/n provides faster web browsing with wider coverage than before, and HSDPA 7.2Mbps downloads large files quickly. Because of the larger battery life, you can do all of this and much more on a single battery charge.<br/><br/><b>Ultimate Integration</b><br/>A one-stop centre for all your messaging, the Social Hub offers you a quick glance status check of all their messages across various platforms including email, instant messaging, social networking and SMS. You won’t have to view different calendars to get their schedule. Various online calendars including Facebook Events are all integrated onto one easy-to-check calendar. You won’t have to look up two separate widgets to check the time and the weather thanks to the Hybrid widgets. Also, there’s a widget to monitor data usage so the phone bill doesn’t get too out of control.<br/><br/><b>Convenience Centre</b><br/>Allshare connects the mobile to TV, computer, stereo system, etc. on a home network so that all media content is shared easily. Typing is much easier, too. With SWYPE, you can input text much faster by swiping their finger across the letters on the screen instead of tapping each individual button.<br/><br/><b>Entertainment Centre</b><br/>With access to the mobile’s many features, you will enjoy fun and entertainment around the clock. Everything from Google Mobile Services to over 2 million applications from the Android Market is available.","longdesc2":"Samsung Galaxy Galaxy Gio. Display diagonal: 8.13 cm (3.2\"), Display resolution: 320 x 480 pixels. Internal storage capacity: 150 GB. Rear camera resolution (numeric): 3 MP, Rear camera type: Single camera. SIM card capability: Single SIM, 3G. Battery capacity: 1350 mAh. Product colour: Silver,White. Weight: 102 g","longdesc3":"","longdesc4":"","mainitemid":0,"packagePriceEnabled":false,"permitnostock":false,"promotions":[{"displayText":"","name":"10off","type":0},{"displayText":"","name":"BuyAnything-Get50%Off","type":0}],"properties":[{"itemid":0,"propdesc":"2G bands (primary SIM)","propgroup":"","propid":0,"propname":"ic_2G_bands_primary_SIM","propnumber":898,"propvalue":"850,900,1800,1900 MHz"},{"itemid":0,"propdesc":"2G standards","propgroup":"","propid":0,"propname":"ic_2G_standards","propnumber":766,"propvalue":"EDGE,GPRS,GSM"},{"itemid":0,"propdesc":"3G","propgroup":"","propid":0,"propname":"ic_3G","propnumber":353,"propvalue":"Yes"},{"itemid":0,"propdesc":"3G standards","propgroup":"","propid":0,"propname":"ic_3G_standards","propnumber":781,"propvalue":"HSDPA"},{"itemid":0,"propdesc":"4G","propgroup":"","propid":0,"propname":"ic_4G","propnumber":782,"propvalue":"No"},{"itemid":0,"propdesc":"Assisted GPS (A-GPS)","propgroup":"","propid":0,"propname":"ic_Assisted_GPS_A_GPS","propnumber":783,"propvalue":"Yes"},{"itemid":0,"propdesc":"Audio formats supported","propgroup":"","propid":0,"propname":"ic_Audio_formats_supported","propnumber":420,"propvalue":"AAC,MIDI,MP3,WAV"},{"itemid":0,"propdesc":"Auto focus","propgroup":"","propid":0,"propname":"ic_Auto_focus","propnumber":784,"propvalue":"Yes"},{"itemid":0,"propdesc":"Battery capacity","propgroup":"","propid":0,"propname":"ic_Battery_capacity","propnumber":288,"propvalue":"1350 mAh"},{"itemid":0,"propdesc":"Battery technology","propgroup":"","propid":0,"propname":"ic_Battery_technology","propnumber":533,"propvalue":"Lithium-Ion (Li-Ion)"},{"itemid":0,"propdesc":"Bluetooth","propgroup":"","propid":0,"propname":"ic_Bluetooth","propnumber":352,"propvalue":"Yes"},{"itemid":0,"propdesc":"Bluetooth version","propgroup":"","propid":0,"propname":"ic_Bluetooth_version","propnumber":767,"propvalue":"3.0+EDR"},{"itemid":0,"propdesc":"Brand","propgroup":"","propid":0,"propname":"ic_Brand","propnumber":168,"propvalue":"Samsung"},{"itemid":0,"propdesc":"Caller ID","propgroup":"","propid":0,"propname":"ic_Caller_ID","propnumber":895,"propvalue":"Yes"},{"itemid":0,"propdesc":"Compatible memory cards","propgroup":"","propid":0,"propname":"ic_Compatible_memory_cards","propnumber":340,"propvalue":"microSD (TransFlash)"},{"itemid":0,"propdesc":"Data network","propgroup":"","propid":0,"propname":"ic_Data_network","propnumber":768,"propvalue":"3G"},{"itemid":0,"propdesc":"Depth","propgroup":"","propid":0,"propname":"ic_Depth","propnumber":188,"propvalue":"12.2 mm"},{"itemid":0,"propdesc":"Digital zoom","propgroup":"","propid":0,"propname":"ic_Digital_zoom","propnumber":769,"propvalue":"3x"},{"itemid":0,"propdesc":"Display diagonal","propgroup":"","propid":0,"propname":"ic_Display_diagonal","propnumber":193,"propvalue":"8.13 cm (3.2\")"},{"itemid":0,"propdesc":"Display number of colours","propgroup":"","propid":0,"propname":"ic_Display_number_of_colours","propnumber":579,"propvalue":"16.78 million colors"},{"itemid":0,"propdesc":"Display resolution","propgroup":"","propid":0,"propname":"ic_Display_resolution","propnumber":195,"propvalue":"320 x 480 pixels"},{"itemid":0,"propdesc":"E-mail","propgroup":"","propid":0,"propname":"ic_E_mail","propnumber":787,"propvalue":"Yes"},{"itemid":0,"propdesc":"Flight mode","propgroup":"","propid":0,"propname":"ic_Flight_mode","propnumber":847,"propvalue":"Yes"},{"itemid":0,"propdesc":"FM radio","propgroup":"","propid":0,"propname":"ic_FM_radio","propnumber":771,"propvalue":"Yes"},{"itemid":0,"propdesc":"Form factor","propgroup":"","propid":0,"propname":"ic_Form_factor","propnumber":772,"propvalue":"Bar"},{"itemid":0,"propdesc":"GPS (satellite)","propgroup":"","propid":0,"propname":"ic_GPS_satellite","propnumber":791,"propvalue":"Yes"},{"itemid":0,"propdesc":"Height","propgroup":"","propid":0,"propname":"ic_Height","propnumber":206,"propvalue":"110.5 mm"},{"itemid":0,"propdesc":"Instant messaging (IM)","propgroup":"","propid":0,"propname":"ic_Instant_messaging_IM","propnumber":794,"propvalue":"Yes"},{"itemid":0,"propdesc":"Internal memory","propgroup":"","propid":0,"propname":"ic_Internal_memory","propnumber":330,"propvalue":""},{"itemid":0,"propdesc":"Internal storage capacity","propgroup":"","propid":0,"propname":"ic_Internal_storage_capacity","propnumber":844,"propvalue":"150 GB"},{"itemid":0,"propdesc":"Maximum frame rate","propgroup":"","propid":0,"propname":"ic_Maximum_frame_rate","propnumber":836,"propvalue":"15 fps"},{"itemid":0,"propdesc":"Maximum memory card size","propgroup":"","propid":0,"propname":"ic_Maximum_memory_card_size","propnumber":796,"propvalue":"32 GB"},{"itemid":0,"propdesc":"MMS (Multimedia Messaging Service)","propgroup":"","propid":0,"propname":"ic_MMS_Multimedia_Messaging_Service","propnumber":774,"propvalue":"Yes"},{"itemid":0,"propdesc":"Personal info management (PIM)","propgroup":"","propid":0,"propname":"ic_Personal_info_management_PIM","propnumber":797,"propvalue":"Alarm clock,Calculator,Calendar,Notes"},{"itemid":0,"propdesc":"Photo effects","propgroup":"","propid":0,"propname":"ic_Photo_effects","propnumber":848,"propvalue":"Black&White,Negative film,Neutral,Sepia"},{"itemid":0,"propdesc":"Platform","propgroup":"","propid":0,"propname":"ic_Platform","propnumber":798,"propvalue":"Android"},{"itemid":0,"propdesc":"Position location","propgroup":"","propid":0,"propname":"ic_Position_location","propnumber":799,"propvalue":"Yes"},{"itemid":0,"propdesc":"Product colour","propgroup":"","propid":0,"propname":"ic_Product_colour","propnumber":226,"propvalue":"Silver,White"},{"itemid":0,"propdesc":"Radio Data System (RDS)","propgroup":"","propid":0,"propname":"ic_Radio_Data_System_RDS","propnumber":800,"propvalue":"Yes"},{"itemid":0,"propdesc":"Rear camera resolution (numeric)","propgroup":"","propid":0,"propname":"ic_Rear_camera_resolution_numeric","propnumber":804,"propvalue":"3 MP"},{"itemid":0,"propdesc":"Rear camera type","propgroup":"","propid":0,"propname":"ic_Rear_camera_type","propnumber":777,"propvalue":"Single camera"},{"itemid":0,"propdesc":"Short Message Service (SMS)","propgroup":"","propid":0,"propname":"ic_Short_Message_Service_SMS","propnumber":806,"propvalue":"Yes"},{"itemid":0,"propdesc":"SIM card capability","propgroup":"","propid":0,"propname":"ic_SIM_card_capability","propnumber":807,"propvalue":"Single SIM"},{"itemid":0,"propdesc":"Speakerphone","propgroup":"","propid":0,"propname":"ic_Speakerphone","propnumber":828,"propvalue":"Yes"},{"itemid":0,"propdesc":"Standby time (2G)","propgroup":"","propid":0,"propname":"ic_Standby_time_2G","propnumber":779,"propvalue":"610 h"},{"itemid":0,"propdesc":"Standby time (3G)","propgroup":"","propid":0,"propname":"ic_Standby_time_3G","propnumber":810,"propvalue":"460 h"},{"itemid":0,"propdesc":"Subscription type","propgroup":"","propid":0,"propname":"ic_Subscription_type","propnumber":811,"propvalue":"No subscription"},{"itemid":0,"propdesc":"Talk time (2G)","propgroup":"","propid":0,"propname":"ic_Talk_time_2G","propnumber":780,"propvalue":"10.6 h"},{"itemid":0,"propdesc":"Talk time (3G)","propgroup":"","propid":0,"propname":"ic_Talk_time_3G","propnumber":812,"propvalue":"6.6 h"},{"itemid":0,"propdesc":"Text prediction system","propgroup":"","propid":0,"propname":"ic_Text_prediction_system","propnumber":813,"propvalue":"Yes"},{"itemid":0,"propdesc":"Text prediction system type","propgroup":"","propid":0,"propname":"ic_Text_prediction_system_type","propnumber":814,"propvalue":"T9"},{"itemid":0,"propdesc":"Touchscreen","propgroup":"","propid":0,"propname":"ic_Touchscreen","propnumber":815,"propvalue":"Yes"},{"itemid":0,"propdesc":"Touch technology","propgroup":"","propid":0,"propname":"ic_Touch_technology","propnumber":912,"propvalue":"Multi-touch"},{"itemid":0,"propdesc":"USB mass storage","propgroup":"","propid":0,"propname":"ic_USB_mass_storage","propnumber":909,"propvalue":"Yes"},{"itemid":0,"propdesc":"USB port","propgroup":"","propid":0,"propname":"ic_USB_port","propnumber":627,"propvalue":"Yes"},{"itemid":0,"propdesc":"USB version","propgroup":"","propid":0,"propname":"ic_USB_version","propnumber":817,"propvalue":"2.0"},{"itemid":0,"propdesc":"Video formats supported","propgroup":"","propid":0,"propname":"ic_Video_formats_supported","propnumber":440,"propvalue":"3GP,H.263,H.264,MPEG4"},{"itemid":0,"propdesc":"Video recording","propgroup":"","propid":0,"propname":"ic_Video_recording","propnumber":845,"propvalue":"Yes"},{"itemid":0,"propdesc":"Weight","propgroup":"","propid":0,"propname":"ic_Weight","propnumber":244,"propvalue":"102 g"},{"itemid":0,"propdesc":"White balance","propgroup":"","propid":0,"propname":"ic_White_balance","propnumber":849,"propvalue":"Auto,Cloudy,Daylight,Fluorescent,Incandescent"},{"itemid":0,"propdesc":"Width","propgroup":"","propid":0,"propname":"ic_Width","propnumber":246,"propvalue":"57.5 mm"},{"itemid":0,"propdesc":"Wi-Fi","propgroup":"","propid":0,"propname":"ic_Wi_Fi","propnumber":248,"propvalue":"Yes"},{"itemid":0,"propdesc":"Wi-Fi standards","propgroup":"","propid":0,"propname":"ic_Wi_Fi_standards","propnumber":461,"propvalue":"802.11b,802.11g,Wi-Fi 4 (802.11n)"},{"itemid":0,"propdesc":"Gallery Images","propgroup":"","propid":0,"propname":"Sys_Gallery_Images","propnumber":169,"propvalue":"4"},{"itemid":0,"propdesc":"Pdf Files","propgroup":"","propid":0,"propname":"Sys_Pdf_Files","propnumber":170,"propvalue":"1"}],"rating":0,"reviews":[],"seoUrl":"","shortdesc":"3.2'' TFT, 320 x 480, 3.2MP, MPEG4, 3GP, H.263, H.264, 802.11 b/g/n, 158MB, MicroSD (32GB), Bluetooth V3.0 + EDR, white silver","showAll":false,"showDistributor":false,"showOutOfStock":false,"skuids":[],"skus":[],"storevid":"20180521148","subscribedcodes":[],"title":"Samsung Galaxy Gio 8 13 cm (3 2&quot;) 150 GB Single SIM Silver White 1350 mAh","vendorId":"20180522154","vendorid":"20180522154"}],"__Success":"true"},"supplierData":{"__Result":[{"code":"AINXF5OVG2","distributorOrder":[{"address":"92 Caplan Ave","city":"Barrie","code":"Barrie Supplier Store","country":"CANADA","customer_service_email":"demo@avetti.ca","customer_service_phone":"0123456789","desc":"Barrie Supplier Store","distid":203,"inUrlId":"supplier1","lat":"10","longitude":"8","name":"Barrie Supplier Store","postal_code":"E1W 1YN","primaryDomain":"demob2b2cpreview2.avetti.io","rating":0,"rating_count":0,"region":"ALBERTA        ","store_hours":"08:30AM - 05:00PM, Monday to Sunday","storefront":"store/20181212828/assets/images/storefront/20181212828.jpg","supplierType":3}],"itemid":296000}],"__Success":"true"},"priceInvData":{"__Result":[{"code":"AINXF5OVG2","invs":[{"code":"AINXF5OVG2","defdelivery":0,"discontinued":false,"distributorId":203,"dropshipminqty":0,"hide":false,"instock":1000,"inventoryid":166682,"itemid":296000,"minorderqty":0,"nextshipdate":"","nextshipqty":0,"ondisplay":false,"onorder":0,"thirdpartycode":"","thirdpartyinventory":false,"thirdpartymessage":""}],"itemid":296000,"prices":[{"awardPoint":0,"currencyid":1141,"discountRate":0,"discount_1":0,"discount_2":0,"discount_3":0,"discount_4":0,"discount_5":0,"distributorId":203,"id":5512497,"itemcode":"AINXF5OVG2","itemid":296000,"langcode":"","listprice":89,"offercode":"","onsale":false,"packagePrices":[],"price_1":89,"price_2":0,"price_3":0,"price_4":0,"price_5":0,"priority":1000,"qty_1":0,"qty_2":0,"qty_3":0,"qty_4":0,"setup":0,"shoppergroupid":0,"vendorid":"20180521148"}]}],"__Success":"true"}}